<?xml version="1.0" encoding="GB2312" standalone="no"?><document.productproposal><mold>11</mold><iron>11</iron><projectdescription>sdfsdf</projectdescription><test>111</test><total>111</total><projectdesc>sssssssssssssssss</projectdesc><customerlinkman>ssssssssssss</customerlinkman><tooling>11</tooling><product><productnumber>123123</productnumber><productdesc>23423</productdesc><customerno>serswfs</customerno><companyno>wfsdf</companyno><docno>sdfsdf</docno><number>11</number><qty>111</qty></product><product><productnumber>1233434</productnumber><productdesc>1123123wqewer</productdesc><customerno>qwr11</customerno><companyno>wwer</companyno><docno>1</docno><number>2</number><qty>1</qty></product><product><productnumber>1123</productnumber><productdesc>2332rdsf</productdesc><customerno>sfsdfsdf</customerno><companyno>sfsd</companyno><docno>sss</docno><number>11</number><qty>11</qty></product><customermail>ssssssss</customermail><customertel>sssssssssss</customertel><technicalrequirements>sdfsdf</technicalrequirements><customerdesc>sssssssssssssssss</customerdesc><packagerequirements>sdfsdf</packagerequirements><workorder>ssssssssssssssss</workorder><schedulerequirements>dfgdfg</schedulerequirements><wfhistory/><trial>11</trial><customerfax>ssssssssssssss</customerfax><samplesource>sssssssssssssssss</samplesource><other>1</other></document.productproposal>